MANIFEST.in
README.md
setup.py
Django_EMS_WhenIWork.egg-info/PKG-INFO
Django_EMS_WhenIWork.egg-info/SOURCES.txt
Django_EMS_WhenIWork.egg-info/dependency_links.txt
Django_EMS_WhenIWork.egg-info/requires.txt
Django_EMS_WhenIWork.egg-info/top_level.txt
ems_wheniwork/VERSION
ems_wheniwork/__init__.py
ems_wheniwork/tests.py
ems_wheniwork/urls.py
ems_wheniwork/utils.py
ems_wheniwork/resources/ems/file/ServiceSoap/GetServiceOrderDetails/27923C8E39741B2003314324BD737511
ems_wheniwork/resources/gws/file/group_sws/v2/group/u_classrm_services_ems_schedulers/effective_member/javerage
ems_wheniwork/resources/gws/file/group_sws/v3/group/u_classrm_services_ems_schedulers/effective_member/javerage
ems_wheniwork/resources/wheniwork/file/2/shifts/_end_2016-01-02T23_59_59_include_allopen_True_start_2016-01-02T00_00_00
ems_wheniwork/resources/wheniwork/file/2/sites/index.html
ems_wheniwork/resources/wheniwork/file/2/users/_location_id_136
ems_wheniwork/static/ems_wheniwork/css/desktop.less
ems_wheniwork/static/ems_wheniwork/css/mobile.less
ems_wheniwork/static/ems_wheniwork/img/fa-caret-down3.png
ems_wheniwork/static/ems_wheniwork/js/main.js
ems_wheniwork/static/vendor/ico/apple-touch-icon-114-precomposed.png
ems_wheniwork/static/vendor/ico/apple-touch-icon-144-precomposed.png
ems_wheniwork/static/vendor/ico/apple-touch-icon-57-precomposed.png
ems_wheniwork/static/vendor/ico/apple-touch-icon-72-precomposed.png
ems_wheniwork/static/vendor/ico/favicon.ico
ems_wheniwork/static/vendor/js/angular-1.2.13.min.js
ems_wheniwork/static/vendor/js/angular-resource-1.2.13.min.js
ems_wheniwork/static/vendor/js/holder-2.3.1.min.js
ems_wheniwork/static/vendor/js/moment.min.js
ems_wheniwork/static/vendor/less/bordered-pulled.less
ems_wheniwork/static/vendor/less/core.less
ems_wheniwork/static/vendor/less/fixed-width.less
ems_wheniwork/static/vendor/less/font-awesome.less
ems_wheniwork/static/vendor/less/icons.less
ems_wheniwork/static/vendor/less/larger.less
ems_wheniwork/static/vendor/less/list.less
ems_wheniwork/static/vendor/less/mixins.less
ems_wheniwork/static/vendor/less/path.less
ems_wheniwork/static/vendor/less/rotated-flipped.less
ems_wheniwork/static/vendor/less/spinning.less
