Metadata-Version: 1.1
Name: Django-EMS-WhenIWork
Version: 0.6
Summary: Django app generate WhenIWork shifts from EMS service orders
Home-page: https://github.com/uw-it-cte/django-ems-wheniwork
Author: UNKNOWN
Author-email: UNKNOWN
License: Apache License, Version 2.0
Platform: UNKNOWN
Classifier: Environment :: Web Environment
Classifier: Framework :: Django
Classifier: Intended Audience :: Developers
Classifier: License :: OSI Approved :: Apache Software License
Classifier: Operating System :: OS Independent
Classifier: Programming Language :: Python
Classifier: Programming Language :: Python :: 2.7
Classifier: Programming Language :: Python :: 3.6
